datasette_matomo/__init__.py
datasette_matomo-0.1.2.dist-info/LICENSE
datasette_matomo-0.1.2.dist-info/METADATA
datasette_matomo-0.1.2.dist-info/WHEEL
datasette_matomo-0.1.2.dist-info/entry_points.txt
datasette_matomo-0.1.2.dist-info/top_level.txt
datasette_matomo-0.1.2.dist-info/RECORD
