Metadata-Version: 2.1
Name: datasette-matomo
Version: 0.1.2
Summary: Add Matomo Web Analytics tracking code to Datasette
Home-page: https://github.com/CentreForDigitalHumanities/datasette-matomo
Author: CentreForDigitalHumanities
Author-email: digitalhumanities@uu.nl
License: Apache License, Version 2.0
Project-URL: Issues, https://github.com/CentreForDigitalHumanities/datasette-matomo/issues
Project-URL: CI, https://github.com/CentreForDigitalHumanities/datasette-matomo/actions
Project-URL: Changelog, https://github.com/CentreForDigitalHumanities/datasette-matomo/releases
Classifier: Framework :: Datasette
Classifier: License :: OSI Approved :: Apache Software License
Requires-Python: >=3.7
License-File: LICENSE
Requires-Dist: datasette
Provides-Extra: test
Requires-Dist: pytest ; extra == 'test'
Requires-Dist: pytest-asyncio ; extra == 'test'
